solaris/__init__.py
solaris/api.py
solaris/static.py
solaris_api-1.0.0.dist-info/LICENSE
solaris_api-1.0.0.dist-info/METADATA
solaris_api-1.0.0.dist-info/WHEEL
solaris_api-1.0.0.dist-info/top_level.txt
solaris_api-1.0.0.dist-info/RECORD
