Metadata-Version: 2.1
Name: solaris-api
Version: 1.0.0
Summary: placeholder.
Home-page: https://github.com/ljc-codes/equities.git
Author: Tiger_Shark
Author-email: na@gmail.com
License: UNKNOWN
Platform: UNKNOWN
Classifier: Programming Language :: Python :: 3
Classifier: License :: OSI Approved :: MIT License
Classifier: Operating System :: OS Independent
Requires-Python: >=3.6
Requires-Dist: urllib3
Requires-Dist: psutil
Requires-Dist: html5lib
Requires-Dist: pandas
Requires-Dist: numpy
Requires-Dist: gql
